grpc_svcs/__init__.py
grpc_svcs/_grpc.py
grpc_svcs/py.typed
grpc_svcs-0.1.2.dist-info/METADATA
grpc_svcs-0.1.2.dist-info/WHEEL
grpc_svcs-0.1.2.dist-info/licenses/LICENSE
grpc_svcs-0.1.2.dist-info/RECORD
